intervul/__init__.py
intervul/_datFiles.py
intervul/general.py
intervul/readgeo.py
intervul/readpos.py
intervul/readposI8.py
intervul/vulInterVtk.py
intervul/writeVTK.py
intervul/datFiles/__init__.py
intervul/datFiles/_common.py
intervul/datFiles/_control_data.py
intervul/datFiles/_general_data.py
intervul/datFiles/_global.py
intervul/datFiles/_problem_data.py
intervul/datFiles/_start.py
intervul/datFiles/control_data/__init__.py
intervul/datFiles/control_data/_definitions.py
intervul/datFiles/control_data/_hourglass.py
intervul/datFiles/control_data/smoothing.py
intervul/datFiles/control_data/solver.py
intervul/datFiles/control_data/hourglass/__init__.py
intervul/datFiles/control_data/hourglass/_definitions.py
intervul/datFiles/general_data/__init__.py
intervul/datFiles/general_data/_definitions.py
intervul/datFiles/general_data/_geometry.py
intervul/datFiles/general_data/_properties.py
intervul/datFiles/general_data/_sets.py
intervul/datFiles/general_data/geometry/__init__.py
intervul/datFiles/general_data/geometry/_definitions.py
intervul/datFiles/general_data/properties/__init__.py
intervul/datFiles/general_data/properties/_definitions.py
intervul/datFiles/general_data/properties/_material_system_of_coordinates.py
intervul/datFiles/general_data/properties/_materials.py
intervul/datFiles/general_data/properties/materials/__init__.py
intervul/datFiles/general_data/properties/materials/_definitions.py
intervul/datFiles/general_data/properties/materials/_smien.py
intervul/datFiles/general_data/sets/__init__.py
intervul/datFiles/general_data/sets/_definitions.py
intervul/datFiles/problem_data/__init__.py
intervul/datFiles/problem_data/_anisotropic_material.py
intervul/datFiles/problem_data/_contact.py
intervul/datFiles/problem_data/_definitions.py
intervul/datFiles/problem_data/_weak_form.py
intervul/datFiles/problem_data/large_strain_disp.py
intervul/datFiles/problem_data/anisotropic_material/__init__.py
intervul-0.0.6.dist-info/LICENSE
intervul-0.0.6.dist-info/METADATA
intervul-0.0.6.dist-info/WHEEL
intervul-0.0.6.dist-info/top_level.txt
intervul-0.0.6.dist-info/RECORD
