Metadata-Version: 2.1
Name: intervul
Version: 0.0.6
Summary: Interfaces for inhouse FEM
Home-page: https://github.com/mpacheco62/intervul
Author: Matias Pacheco
Author-email: Matias.Pacheco.A@gmail.com
License: UNKNOWN
Platform: UNKNOWN
Classifier: Programming Language :: Python :: 3
Classifier: License :: OSI Approved :: MIT License
Classifier: Operating System :: POSIX :: Linux
Requires-Python: >=3
Requires-Dist: scipy
